pyobo/.DS_Store
pyobo/__init__.py
pyobo/__main__.py
pyobo/api/__init__.py
pyobo/api/alts.py
pyobo/api/combine.py
pyobo/api/edges.py
pyobo/api/embedding.py
pyobo/api/hierarchy.py
pyobo/api/metadata.py
pyobo/api/names.py
pyobo/api/properties.py
pyobo/api/relations.py
pyobo/api/species.py
pyobo/api/typedefs.py
pyobo/api/utils.py
pyobo/api/xrefs.py
pyobo/cli/__init__.py
pyobo/cli/cli.py
pyobo/cli/database.py
pyobo/cli/database_utils.py
pyobo/cli/lookup.py
pyobo/cli/utils.py
pyobo/constants.py
pyobo/getters.py
pyobo/gilda_utils.py
pyobo/identifier_utils/__init__.py
pyobo/identifier_utils/api.py
pyobo/identifier_utils/relations/__init__.py
pyobo/identifier_utils/relations/api.py
pyobo/identifier_utils/relations/data.json
pyobo/identifier_utils/relations/data_owl.json
pyobo/identifier_utils/relations/data_rdf.json
pyobo/identifier_utils/relations/data_rdfs.json
pyobo/mocks.py
pyobo/ner/__init__.py
pyobo/ner/api.py
pyobo/ner/normalizer.py
pyobo/ner/scispacy_utils.py
pyobo/plugins.py
pyobo/py.typed
pyobo/resource_utils.py
pyobo/resources/__init__.py
pyobo/resources/ncbitaxon.py
pyobo/resources/ncbitaxon.tsv.gz
pyobo/resources/ro.py
pyobo/resources/ro.tsv
pyobo/resources/so.py
pyobo/resources/so.tsv
pyobo/sources/README.md
pyobo/sources/__init__.py
pyobo/sources/agrovoc.py
pyobo/sources/antibodyregistry.py
pyobo/sources/bigg/__init__.py
pyobo/sources/bigg/bigg_compartment.py
pyobo/sources/bigg/bigg_metabolite.py
pyobo/sources/bigg/bigg_model.py
pyobo/sources/bigg/bigg_reaction.py
pyobo/sources/biogrid.py
pyobo/sources/ccle.py
pyobo/sources/cgnc.py
pyobo/sources/chebi.py
pyobo/sources/chembl/__init__.py
pyobo/sources/chembl/chembl_cell.py
pyobo/sources/chembl/chembl_compound.py
pyobo/sources/chembl/chembl_mechanism.py
pyobo/sources/chembl/chembl_target.py
pyobo/sources/chembl/chembl_tissue.py
pyobo/sources/civic_gene.py
pyobo/sources/clinicaltrials.py
pyobo/sources/complexportal.py
pyobo/sources/conso.py
pyobo/sources/cpt.py
pyobo/sources/credit.py
pyobo/sources/cvx.py
pyobo-0.12.15.dist-info/licenses/LICENSE
pyobo-0.12.15.dist-info/WHEEL
pyobo-0.12.15.dist-info/entry_points.txt
pyobo-0.12.15.dist-info/METADATA
pyobo-0.12.15.dist-info/RECORD
