Metadata-Version: 2.4
Name: pyobo
Version: 0.12.15
Summary: A python package for handling and generating OBO
Keywords: snekpack,cookiecutter,ontologies,biomedical ontologies,life sciences,natural sciences,bioinformatics,cheminformatics,Open Biomedical Ontologies,OBO
Author: Charles Tapley Hoyt
Author-email: Charles Tapley Hoyt <cthoyt@gmail.com>
License-File: LICENSE
Classifier: Development Status :: 4 - Beta
Classifier: Environment :: Console
Classifier: Intended Audience :: Developers
Classifier: License :: OSI Approved :: MIT License
Classifier: Operating System :: OS Independent
Classifier: Framework :: Pytest
Classifier: Framework :: tox
Classifier: Framework :: Sphinx
Classifier: Natural Language :: English
Classifier: Programming Language :: Python
Classifier: Programming Language :: Python :: 3.10
Classifier: Programming Language :: Python :: 3.11
Classifier: Programming Language :: Python :: 3.12
Classifier: Programming Language :: Python :: 3.13
Classifier: Programming Language :: Python :: 3 :: Only
Classifier: Typing :: Typed
Classifier: Topic :: Scientific/Engineering :: Bio-Informatics
Classifier: Topic :: Scientific/Engineering :: Chemistry
Requires-Dist: obonet>=0.3.0
Requires-Dist: click
Requires-Dist: tqdm
Requires-Dist: pyyaml
Requires-Dist: pandas
Requires-Dist: requests
Requires-Dist: more-itertools
Requires-Dist: more-click>=0.0.2
Requires-Dist: humanize
Requires-Dist: tabulate
Requires-Dist: cachier
Requires-Dist: pystow>=0.7.5
Requires-Dist: bioversions>=0.8.101
Requires-Dist: bioregistry>=0.12.30
Requires-Dist: bioontologies>=0.7.2
Requires-Dist: ssslm>=0.0.13
Requires-Dist: zenodo-client>=0.4.1
Requires-Dist: class-resolver>=0.6.0
Requires-Dist: pydantic>=2.0
Requires-Dist: curies>=0.10.17
Requires-Dist: curies-processing>=0.1.6
Requires-Dist: python-dateutil
Requires-Dist: networkx>=3.4
Requires-Dist: drugbank-downloader
Requires-Dist: chembl-downloader
Requires-Dist: umls-downloader>=0.1.3
Requires-Dist: clinicaltrials-downloader>=0.0.2
Requires-Dist: nih-reporter-downloader>=0.0.1
Requires-Dist: typing-extensions
Requires-Dist: rdflib
Requires-Dist: obographs>=0.0.8
Requires-Dist: sssom-pydantic>=0.1.1
Requires-Dist: psycopg2-binary ; extra == 'drugcentral'
Requires-Dist: ssslm[gilda] ; extra == 'gilda'
Requires-Dist: ssslm[gilda-slim] ; extra == 'gilda-slim'
Requires-Dist: grape ; extra == 'grape'
Requires-Dist: embiggen ; extra == 'grape'
Requires-Dist: ensmallen ; extra == 'grape'
Requires-Dist: protmapper ; extra == 'pid'
Requires-Dist: pykeen ; extra == 'pykeen'
Requires-Dist: scispacy ; python_full_version < '3.13' and extra == 'scispacy'
Requires-Dist: spacy ; python_full_version < '3.13' and extra == 'scispacy'
Requires-Dist: scipy<1.11 ; python_full_version < '3.13' and extra == 'scispacy'
Requires-Dist: pyobo[drugcentral,pid] ; extra == 'sources'
Maintainer: Charles Tapley Hoyt
Maintainer-email: Charles Tapley Hoyt <cthoyt@gmail.com>
Requires-Python: >=3.10
Project-URL: Bug Tracker, https://github.com/biopragmatics/pyobo/issues
Project-URL: Documentation, https://pyobo.readthedocs.io
Project-URL: Funding, https://github.com/sponsors/cthoyt
Project-URL: Homepage, https://github.com/biopragmatics/pyobo
Project-URL: Repository, https://github.com/biopragmatics/pyobo.git
Provides-Extra: drugcentral
Provides-Extra: gilda
Provides-Extra: gilda-slim
Provides-Extra: grape
Provides-Extra: pid
Provides-Extra: pykeen
Provides-Extra: scispacy
Provides-Extra: sources
